lightswitch/__init__.py
lightswitch/custom_sseclient.py
lightswitch/exceptions.py
lightswitch/lightswitch.py
lightswitch/models.py
lightswitch/stream_manager.py
lightswitch/utils.py
lightswitch_kr-0.1.4.dist-info/METADATA
lightswitch_kr-0.1.4.dist-info/WHEEL
lightswitch_kr-0.1.4.dist-info/RECORD
