Metadata-Version: 2.1
Name: lightswitch_kr
Version: 0.1.4
Summary: A simple SDK for your API
License: MIT
Author: sumtuckyi
Author-email: sumin510@naver.com
Requires-Python: >=3.9,<4.0
Classifier: License :: OSI Approved :: MIT License
Classifier: Programming Language :: Python :: 3
Classifier: Programming Language :: Python :: 3.9
Classifier: Programming Language :: Python :: 3.10
Classifier: Programming Language :: Python :: 3.11
Classifier: Programming Language :: Python :: 3.12
Requires-Dist: requests (>=2.31.0,<3.0.0)
Requires-Dist: sseclient (>=0.0.27,<0.0.28)
Requires-Dist: urllib3 (>=2.2.1,<3.0.0)
